rxn/utilities/__init__.py
rxn/utilities/attrs.py
rxn/utilities/basic.py
rxn/utilities/caching.py
rxn/utilities/containers.py
rxn/utilities/files.py
rxn/utilities/logging.py
rxn/utilities/misc.py
rxn/utilities/py.typed
rxn/utilities/regex.py
rxn/utilities/strings.py
rxn/utilities/types.py
rxn/utilities/csv/__init__.py
rxn/utilities/csv/column_iterator.py
rxn/utilities/csv/csv_iterator.py
rxn/utilities/csv/streaming_csv_editor.py
rxn/utilities/databases/__init__.py
rxn/utilities/databases/pymongo.py
rxn/utilities/modeling/__init__.py
rxn/utilities/modeling/core.py
rxn/utilities/modeling/tokenization.py
rxn/utilities/modeling/utils.py
rxn/utilities/scripts/__init__.py
rxn/utilities/scripts/extract_csv_column.py
rxn/utilities/scripts/stable_shuffle.py
rxn_utils-2.0.0.dist-info/LICENSE
rxn_utils-2.0.0.dist-info/METADATA
rxn_utils-2.0.0.dist-info/WHEEL
rxn_utils-2.0.0.dist-info/entry_points.txt
rxn_utils-2.0.0.dist-info/top_level.txt
rxn_utils-2.0.0.dist-info/RECORD
