Metadata-Version: 2.1
Name: rxn-utils
Version: 2.0.0
Summary: General utilities (not related to chemistry)
Home-page: https://github.com/rxn4chemistry/rxn-utilities
Author: IBM RXN team
Author-email: rxn4chemistry@zurich.ibm.com
License: MIT
Project-URL: Documentation, https://rxn4chemistry.github.io/rxn-utilities/
Project-URL: Repository, https://github.com/rxn4chemistry/rxn-utilities
Classifier: Operating System :: OS Independent
Classifier: Programming Language :: Python :: 3
Classifier: Programming Language :: Python :: 3.7
Classifier: Programming Language :: Python :: 3.8
Classifier: Programming Language :: Python :: 3.9
Classifier: Programming Language :: Python :: 3.10
Classifier: Programming Language :: Python :: 3.11
Requires-Python: >=3.7
License-File: LICENSE
Requires-Dist: attrs >=21.2.0
Requires-Dist: click >=8.0
Requires-Dist: diskcache >=5.2.1
Requires-Dist: pydantic >=1.9.0
Requires-Dist: pydantic-settings >=2.1.0
Requires-Dist: pymongo >=3.9.0
Requires-Dist: tqdm >=4.31.0
Requires-Dist: typing-extensions >=4.1.1
Provides-Extra: dev
Requires-Dist: black >=22.3.0 ; extra == 'dev'
Requires-Dist: bump2version >=1.0.1 ; extra == 'dev'
Requires-Dist: flake8 >=3.7.9 ; extra == 'dev'
Requires-Dist: isort >=5.10.1 ; extra == 'dev'
Requires-Dist: mypy >=0.910 ; extra == 'dev'
Requires-Dist: pytest-cov >=2.8.1 ; extra == 'dev'
Requires-Dist: pytest >=7.0.1 ; extra == 'dev'
Requires-Dist: types-setuptools >=57.4.14 ; extra == 'dev'
Requires-Dist: types-tqdm >=4.64.0 ; extra == 'dev'
Provides-Extra: modeling
Requires-Dist: torch <2.0.0,>=1.5.0 ; extra == 'modeling'
Requires-Dist: transformers >=4.21.0 ; extra == 'modeling'
